asro_preprocessing/__init__.py
asro_preprocessing/core.py
asro_preprocessing/data/kamuskatabaku.xlsx
asro_preprocessing/data/news_dictionary.txt
asro_preprocessing/data/stopwords.txt
asro_preprocessing-0.1.8.dist-info/LICENSE
asro_preprocessing-0.1.8.dist-info/METADATA
asro_preprocessing-0.1.8.dist-info/WHEEL
asro_preprocessing-0.1.8.dist-info/top_level.txt
asro_preprocessing-0.1.8.dist-info/RECORD
