Metadata-Version: 2.2
Name: asro_preprocessing
Version: 0.1.8
Summary: Library untuk preprocessing teks bahasa Indonesia.
Home-page: https://github.com/asroharun6/asro_preprocessing
Author: Asro
Author-email: asro@raharja.info
License: MIT
Classifier: Programming Language :: Python :: 3
Classifier: License :: OSI Approved :: MIT License
Classifier: Operating System :: OS Independent
Requires-Python: >=3.6
License-File: LICENSE
Requires-Dist: pandas
Requires-Dist: nltk
Requires-Dist: openpyxl
Dynamic: author
Dynamic: author-email
Dynamic: classifier
Dynamic: description
Dynamic: description-content-type
Dynamic: home-page
Dynamic: license
Dynamic: requires-dist
Dynamic: requires-python
Dynamic: summary
